{"ID":5970,"Author":{"Name":"hupili","ID":0,"FullName":"","Gravatar":"44ba5ab0ceceafd8b79c5ca236f16b2a"},"Title":"Demo of SNSAPI's CDE Package","Description":"\u003cdiv class=\"content\"\u003e\u003cp\u003eThe CDE package further reduces the headache of first timers. There is a one-liner to get everything ready. We have already configured test channels with credentials on several Online Social Networks, so that you can start to play around immediately.\u003c/p\u003e\n\n\u003cp\u003eSee the download script:\u003c/p\u003e\n\n\u003cp\u003e\u003ca href=\"https://gist.github.com/hupili/7020251\"\u003ehttps://gist.github.com/hupili/7020251\u003c/a\u003e\u003c/p\u003e\n\u003c/div\u003e","Time":"2013-10-17T10:21:53Z","Tags":["Linux","bash","xterm"]}